scrapy_po/__init__.py
scrapy_po/middleware.py
scrapy_po/page_input_providers.py
scrapy_po/page_inputs.py
scrapy_po/utils.py
scrapy_po/webpage.py
scrapy_po-0.0.1.dist-info/LICENSE
scrapy_po-0.0.1.dist-info/METADATA
scrapy_po-0.0.1.dist-info/WHEEL
scrapy_po-0.0.1.dist-info/top_level.txt
scrapy_po-0.0.1.dist-info/RECORD
