Metadata-Version: 2.1
Name: scrapy-po
Version: 0.0.1
Summary: Page Object pattern for Scrapy
Home-page: https://github.com/scrapinghub/scrapy-po
Author: Mikhail Korobov
Author-email: kmike84@gmail.com
License: UNKNOWN
Platform: UNKNOWN
Classifier: Development Status :: 2 - Pre-Alpha
Classifier: Intended Audience :: Developers
Classifier: License :: OSI Approved :: BSD License
Classifier: Natural Language :: English
Classifier: Operating System :: OS Independent
Classifier: Framework :: Scrapy
Classifier: Programming Language :: Python :: 3
Classifier: Programming Language :: Python :: 3.6
Classifier: Programming Language :: Python :: 3.7
Requires-Dist: andi
Requires-Dist: attrs
Requires-Dist: parsel
